[{
  "firstName": "Иван",
  "lastName": "Иванов",
  "address": "г.Москва, ул. Алиева,2",
  "phoneNumber": "812 123-1234"
}, {
  "firstName": "Петр",
  "lastName": "Петров",
  "address": "г.Санкт-Петербург, ул. Попова,2",
  "phoneNumber": "125 497-0354"
}, {
  "firstName": "Сергей",
  "lastName": "Сергеев",
  "address": "г.Владивосток, ул. Менделеева,2",
  "phoneNumber": "756 215-7843"
}, {
  "firstName": "Николай",
  "lastName": "Николаев",
  "address": "г.Хабаровск, ул. Лобачевского,5",
  "phoneNumber": "487 158-0054"
}, {
  "firstName": "Семен",
  "lastName": "Семенов",
  "address": "г.Томск, ул. Ломоносова,6",
  "phoneNumber": "745 156-7845"
}]